analyticord/__init__.py
analyticord/analyticord.py
analyticord/errors.py
analyticord-0.3.0.dist-info/DESCRIPTION.rst
analyticord-0.3.0.dist-info/METADATA
analyticord-0.3.0.dist-info/RECORD
analyticord-0.3.0.dist-info/WHEEL
analyticord-0.3.0.dist-info/metadata.json
analyticord-0.3.0.dist-info/top_level.txt
tests/__init__.py
tests/conftest.py
tests/test_analytics.py
