Metadata-Version: 2.0
Name: analyticord
Version: 0.3.0
Summary: UNKNOWN
Home-page: https://github.com/nitros12/analyticord
Author: Ben Simms
Author-email: ben@bensimms.moe
License: MIT
Platform: UNKNOWN
Classifier: Development Status :: 4 - Beta
Classifier: Intended Audience :: Developers
Classifier: License :: OSI Approved :: MIT License
Classifier: Operating System :: OS Independent
Classifier: Programming Language :: Python :: 3.5
Classifier: Programming Language :: Python :: 3.6
Classifier: Programming Language :: Python :: Implementation :: CPython
Requires-Dist: aiohttp
Provides-Extra: docs
Requires-Dist: sphinx-autodoc-typehints (>=1.2.1); extra == 'docs'
Requires-Dist: sphinxcontrib-asyncio; extra == 'docs'
